README.md
setup.py
kanobu_server/__init__.py
kanobu_server/__main__.py
kanobu_server/client.py
kanobu_server/server.py
kanobu_server.egg-info/PKG-INFO
kanobu_server.egg-info/SOURCES.txt
kanobu_server.egg-info/dependency_links.txt
kanobu_server.egg-info/entry_points.txt
kanobu_server.egg-info/top_level.txt